{
  "id": "event-0640-campaigns-of-the-muslims-and-other-matters",
  "title": "The Campaigns of the Muslims and Other Matters",
  "description": "Tabari said: According to Ibn Humayd -Salamah- Ibn Ishaq: (2580] Egypt547 was conquered in this year. It was conquered in the year 20 (641). Abu Ma'shar has the same (date); according to Ahmad b. Thabit-his authority-Ishaq b. 'Isa-himself: Egypt was conquered in the year 20 (641), the Muslim commander was 'Amr b. al-'A$i.",
  "startDate": "0640-01-01",
  "category": "military",
  "connections": [],
  "confidence": "auto-imported",
  "sources": [
    {
      "citation": "al-Tabari, The History of al-Tabari (SUNY), vol. 13",
      "page": "162"
    }
  ]
}