{
  "id": "event-0833-al-ma-mun-s-orders-to-his-governor",
  "title": "Al-Ma'mun's orders to his governor in Baghdad, Ishaq b. Ibrahim al-Mus'abi, to interrogate the judges and traditionists on the question of the createdness of the Qur'an: the Caliph's first letter",
  "description": "Al-Ma'mun's orders to his governor in Baghdad, Ishaq b. Ibrahim al-Mus'abi, to interrogate the judges and traditionists on the question of the createdness of the Qur'an: the Caliph's first letter. Recorded under the year 218 AH (833–834 CE) in al-Tabari's History, volume 32.",
  "startDate": "0833-01-27",
  "category": "political",
  "connections": [
    "event-0825-capture-of-ibrahim-b-al-mahdi-dressed-in",
    "event-0833-ishaq-s-interrogation-at-baghdad-of-a-further"
  ],
  "confidence": "auto-imported",
  "endDate": "0834-01-15",
  "location": {
    "latitude": 33.3152,
    "longitude": 44.3661,
    "name": "Baghdad, Iraq"
  },
  "sources": [
    {
      "citation": "al-Tabari, The History of al-Tabari (SUNY), vol. 32",
      "page": "199"
    }
  ]
}